fabric_hydrate/__init__.py
fabric_hydrate/cli.py
fabric_hydrate/delta_reader.py
fabric_hydrate/diff_engine.py
fabric_hydrate/exceptions.py
fabric_hydrate/fabric_client.py
fabric_hydrate/logging.py
fabric_hydrate/metadata_generator.py
fabric_hydrate/models.py
fabric_hydrate/py.typed
fabric_hydrate/retry.py
fabric_hydrate-1.0.1.dist-info/METADATA
fabric_hydrate-1.0.1.dist-info/WHEEL
fabric_hydrate-1.0.1.dist-info/entry_points.txt
fabric_hydrate-1.0.1.dist-info/licenses/LICENSE
fabric_hydrate-1.0.1.dist-info/RECORD
