Metadata-Version: 2.4
Name: fabric-hydrate
Version: 1.0.1
Summary: A CLI tool to hydrate Microsoft Fabric Lakehouse metadata from Delta Lake schemas
Project-URL: Homepage, https://github.com/mjtpena/fabric-hydrate
Project-URL: Documentation, https://github.com/mjtpena/fabric-hydrate#readme
Project-URL: Repository, https://github.com/mjtpena/fabric-hydrate
Project-URL: Issues, https://github.com/mjtpena/fabric-hydrate/issues
Author-email: Michael John Peña <mjtpena@outlook.com>
Maintainer-email: Michael John Peña <mjtpena@outlook.com>
License-Expression: MIT
License-File: LICENSE
Keywords: azure,cli,data-engineering,delta-lake,lakehouse,metadata,microsoft-fabric,onelake,schema
Classifier: Development Status :: 4 - Beta
Classifier: Environment :: Console
Classifier: Intended Audience :: Developers
Classifier: Intended Audience :: System Administrators
Classifier: License :: OSI Approved :: MIT License
Classifier: Operating System :: OS Independent
Classifier: Programming Language :: Python :: 3
Classifier: Programming Language :: Python :: 3.10
Classifier: Programming Language :: Python :: 3.11
Classifier: Programming Language :: Python :: 3.12
Classifier: Programming Language :: Python :: 3.13
Classifier: Topic :: Database
Classifier: Topic :: Software Development :: Libraries :: Python Modules
Classifier: Topic :: System :: Systems Administration
Classifier: Typing :: Typed
Requires-Python: >=3.10
Requires-Dist: azure-identity>=1.15.0
Requires-Dist: deltalake>=0.18.0
Requires-Dist: httpx>=0.27.0
Requires-Dist: pydantic>=2.6.0
Requires-Dist: pyyaml>=6.0.0
Requires-Dist: rich>=13.7.0
Requires-Dist: typer>=0.12.0
Provides-Extra: all
Requires-Dist: mkdocs-material>=9.5.0; extra == 'all'
Requires-Dist: mkdocs>=1.5.0; extra == 'all'
Requires-Dist: mkdocstrings[python]>=0.24.0; extra == 'all'
Requires-Dist: mypy>=1.8.0; extra == 'all'
Requires-Dist: pre-commit>=3.6.0; extra == 'all'
Requires-Dist: pyarrow>=14.0.0; extra == 'all'
Requires-Dist: pytest-asyncio>=0.23.0; extra == 'all'
Requires-Dist: pytest-cov>=4.1.0; extra == 'all'
Requires-Dist: pytest>=8.0.0; extra == 'all'
Requires-Dist: ruff>=0.3.0; extra == 'all'
Requires-Dist: types-pyyaml>=6.0.0; extra == 'all'
Provides-Extra: dev
Requires-Dist: mypy>=1.8.0; extra == 'dev'
Requires-Dist: pre-commit>=3.6.0; extra == 'dev'
Requires-Dist: pyarrow>=14.0.0; extra == 'dev'
Requires-Dist: pytest-asyncio>=0.23.0; extra == 'dev'
Requires-Dist: pytest-cov>=4.1.0; extra == 'dev'
Requires-Dist: pytest>=8.0.0; extra == 'dev'
Requires-Dist: ruff>=0.3.0; extra == 'dev'
Requires-Dist: types-pyyaml>=6.0.0; extra == 'dev'
Provides-Extra: docs
Requires-Dist: mkdocs-material>=9.5.0; extra == 'docs'
Requires-Dist: mkdocs>=1.5.0; extra == 'docs'
Requires-Dist: mkdocstrings[python]>=0.24.0; extra == 'docs'
